sysmon/__init__.py
sysmon/cli.py
sysmon_cli-0.2.0.dist-info/METADATA
sysmon_cli-0.2.0.dist-info/WHEEL
sysmon_cli-0.2.0.dist-info/entry_points.txt
sysmon_cli-0.2.0.dist-info/top_level.txt
sysmon_cli-0.2.0.dist-info/RECORD
