Metadata-Version: 2.4
Name: sysmon-cli
Version: 0.2.0
Summary: System Monitor - GPU, CPU, Memory, Disk status like gpustat
Project-URL: Homepage, https://github.com/lancl/sysmon
Keywords: gpu,nvidia,monitor,system,gpustat
Classifier: Programming Language :: Python :: 3
Classifier: Operating System :: POSIX :: Linux
Classifier: Environment :: Console
Classifier: Environment :: Console :: Curses
Classifier: License :: OSI Approved :: MIT License
Requires-Python: >=3.7
